htstabilizer/__init__.py
htstabilizer/circuit_lookup.py
htstabilizer/connectivity_support.py
htstabilizer/f2_algebra.py
htstabilizer/find_local_clifford_layer.py
htstabilizer/graph.py
htstabilizer/graph_draw.py
htstabilizer/lc_classes.py
htstabilizer/linear_index.py
htstabilizer/mub_circuits.py
htstabilizer/rotate_stabilizer_into_state.py
htstabilizer/stabilizer.py
htstabilizer/stabilizer_circuits.py
htstabilizer/tomography.py
htstabilizer/data/__init__.py
htstabilizer/data/mub2-all.txt
htstabilizer/data/mub3-all.txt
htstabilizer/data/mub3-linear.txt
htstabilizer/data/mub4-all.txt
htstabilizer/data/mub4-cycle.txt
htstabilizer/data/mub4-linear.txt
htstabilizer/data/mub4-star.txt
htstabilizer/data/mub5-Q.txt
htstabilizer/data/mub5-T.txt
htstabilizer/data/mub5-all.txt
htstabilizer/data/mub5-cycle.txt
htstabilizer/data/mub5-linear.txt
htstabilizer/data/mub5-star.txt
htstabilizer/data/mub6-E.txt
htstabilizer/data/mub6-Ez.txt
htstabilizer/data/mub6-H.txt
htstabilizer/data/mub6-Q.txt
htstabilizer/data/mub6-all.txt
htstabilizer/data/mub6-ladder.txt
htstabilizer/data/mub6-linear.txt
htstabilizer/data/mub6-star.txt
htstabilizer/data/stabilizer2-all.txt
htstabilizer/data/stabilizer3-all.txt
htstabilizer/data/stabilizer3-linear.txt
htstabilizer/data/stabilizer4-all.txt
htstabilizer/data/stabilizer4-cycle.txt
htstabilizer/data/stabilizer4-linear.txt
htstabilizer/data/stabilizer4-star.txt
htstabilizer/data/stabilizer5-Q.txt
htstabilizer/data/stabilizer5-T.txt
htstabilizer/data/stabilizer5-all.txt
htstabilizer/data/stabilizer5-cycle.txt
htstabilizer/data/stabilizer5-linear.txt
htstabilizer/data/stabilizer5-star.txt
htstabilizer/data/stabilizer6-E.txt
htstabilizer/data/stabilizer6-H.txt
htstabilizer/data/stabilizer6-Q.txt
htstabilizer/data/stabilizer6-all.txt
htstabilizer/data/stabilizer6-allx.txt
htstabilizer/data/stabilizer6-ladder.txt
htstabilizer/data/stabilizer6-linear.txt
htstabilizer/data/stabilizer6-star.txt
htstabilizer-1.0.1.dist-info/licenses/LICENSE.txt
htstabilizer-1.0.1.dist-info/METADATA
htstabilizer-1.0.1.dist-info/WHEEL
htstabilizer-1.0.1.dist-info/top_level.txt
htstabilizer-1.0.1.dist-info/RECORD
