Metadata-Version: 2.4
Name: htstabilizer
Version: 1.0.1
Summary: Hardware-tailored quantum Clifford circuits for stabilizer state preparation or readout as well as mutually unbiased bases in order to perform efficient full-state tomography on small qubit systems.
Author: Mc-Zen
License: MIT License
Project-URL: Homepage, https://github.com/Mc-Zen/htstabilizer
Project-URL: Bug Tracker, https://github.com/Mc-Zen/htstabilizer/issues
Keywords: quantum circuits,clifford,hardware-tailored,full-state tomography,stabilizer,quantum state preparation,quantum readout circuits,mutually unbiased bases,short circuits,full state tomography,circuit optimization
Classifier: Programming Language :: Python :: 3
Classifier: License :: OSI Approved :: MIT License
Classifier: Operating System :: OS Independent
Requires-Python: >=3.10
License-File: LICENSE.txt
Requires-Dist: qiskit>=0.39
Requires-Dist: numpy>=1.22
Dynamic: license-file
